s4/platform/.env
s4/platform/__init__.py
s4/platform/api.py
s4/platform/authentication_utils.py
s4/platform/changeset/changeset.py
s4/platform/changeset/changeset_config.py
s4/platform/changeset/deploy_changeset.py
s4/platform/claim/claim.py
s4/platform/config/config.py
s4/platform/connection.py
s4/platform/constants.py
s4/platform/deployment/deployment.py
s4/platform/entity/ad_hoc_entity.py
s4/platform/entity/entity.py
s4/platform/entity/field_value.py
s4/platform/entity_location/entity_location.py
s4/platform/entity_type/entity_type.py
s4/platform/environment/environment.py
s4/platform/environment/environment_configuration.py
s4/platform/environment/migration_plan.py
s4/platform/faas/custom_errors.py
s4/platform/faas/faas_function.py
s4/platform/faas/faas_utils.py
s4/platform/file/file_reference.py
s4/platform/function/function.py
s4/platform/function/lambda_function.py
s4/platform/internal/base_model.py
s4/platform/internal/base_schema.py
s4/platform/internal/camel_case_schema.py
s4/platform/internal/fields_mixin.py
s4/platform/internal/lazy_property.py
s4/platform/internal/lazy_property_list.py
s4/platform/internal/sort_direction.py
s4/platform/link_config/__init__.py
s4/platform/link_config/link_config.py
s4/platform/link_config/new_workbook_link.py
s4/platform/page_config/page_config.py
s4/platform/page_config/page_container.py
s4/platform/page_config/page_container_page_config.py
s4/platform/prospective_task/ProspectiveTaskSummary.py
s4/platform/prospective_task/function_list.py
s4/platform/prospective_task/function_status.py
s4/platform/prospective_task/io_group.py
s4/platform/prospective_task/prospective_entity.py
s4/platform/prospective_task/prospective_field_value.py
s4/platform/prospective_task/prospective_task.py
s4/platform/prospective_task/search.py
s4/platform/prospective_task_config/copy_forward_config.py
s4/platform/prospective_task_config/field_config.py
s4/platform/prospective_task_config/field_type.py
s4_platform_api-1.9.1.dist-info/METADATA
s4_platform_api-1.9.1.dist-info/WHEEL
s4_platform_api-1.9.1.dist-info/licenses/LICENSE
s4_platform_api-1.9.1.dist-info/RECORD
